kevbase64/__init__.py
kevbase64/__main__.py
kevbase64/decode.py
kevbase64/encode.py
kevbase64/main.py
kevbase64/table.py
kevbase64-0.2.dist-info/LICENSE
kevbase64-0.2.dist-info/METADATA
kevbase64-0.2.dist-info/WHEEL
kevbase64-0.2.dist-info/entry_points.txt
kevbase64-0.2.dist-info/top_level.txt
kevbase64-0.2.dist-info/RECORD
