Metadata-Version: 2.1
Name: kevbase64
Version: 0.2
Summary: Encode and decode using Base64 representation with Kev's implementation
Requires-Python: >=3.11
License-File: LICENSE
